lognet/__init__.py
lognet/core/__init__.py
lognet/core/application/__init__.py
lognet/core/application/logger.py
lognet/core/application/formatters/__init__.py
lognet/core/application/formatters/log_formatter.py
lognet/core/application/handlers/__init__.py
lognet/core/application/handlers/console_handler.py
lognet/core/application/handlers/file_handler.py
lognet/core/application/handlers/handler.py
lognet/core/configuration/__init__.py
lognet/core/configuration/handler_configurator.py
lognet/core/configuration/logger_config.py
lognet/core/domain/__init__.py
lognet/core/domain/log_entity.py
lognet-3.0.2.dist-info/LICENSE
lognet-3.0.2.dist-info/METADATA
lognet-3.0.2.dist-info/WHEEL
lognet-3.0.2.dist-info/top_level.txt
lognet-3.0.2.dist-info/RECORD
