Metadata-Version: 2.1
Name: lognet
Version: 3.0.2
Summary: A simple logger with a convenient log message format.
Home-page: https://github.com/Noloquideus/Lognet
Author: Noloquideus
Author-email: daniilmanukian@gmail.com
License: MIT License
Keywords: lognet,logging,logger,log
Classifier: Programming Language :: Python
Classifier: Programming Language :: Python :: 3
Classifier: Programming Language :: Python :: 3.5
Classifier: Programming Language :: Python :: 3.6
Classifier: Programming Language :: Python :: 3.7
Classifier: Programming Language :: Python :: 3.8
Classifier: Programming Language :: Python :: 3.9
Classifier: Programming Language :: Python :: 3.10
Classifier: Programming Language :: Python :: 3.11
Classifier: Programming Language :: Python :: 3.12
Classifier: Programming Language :: Python :: 3 :: Only
Classifier: License :: OSI Approved :: MIT License
Classifier: Operating System :: OS Independent
Requires-Python: >=3.5
License-File: LICENSE
